[
  {
    "A_name" : "FollowingAPI",
    "B_kind" : "enum",
    "C_accessLevel" : "public",
    "D_attributes" : [

    ],
    "E_adoptedClassProtocols" : [

    ],
    "F_location" : "FollowingAPI.swift - Line: 11, Column: 1",
    "G_members" : [
      {
        "A_name" : "follow",
        "B_kind" : "case",
        "C_accessLevel" : "internal",
        "D_attributes" : [

        ],
        "F_location" : "FollowingAPI.swift - Line: 12, Column: 10",
        "I_parameterType" : [
          "Int64"
        ],
        "I_parameters" : [
          "targetUserId"
        ]
      },
      {
        "A_name" : "unfollow",
        "B_kind" : "case",
        "C_accessLevel" : "internal",
        "D_attributes" : [

        ],
        "F_location" : "FollowingAPI.swift - Line: 13, Column: 10",
        "I_parameterType" : [
          "Int64"
        ],
        "I_parameters" : [
          "targetUserId"
        ]
      }
    ]
  },
  {
    "A_name" : "FollowingAPI",
    "B_kind" : "extension",
    "C_accessLevel" : "internal",
    "D_attributes" : [

    ],
    "E_adoptedClassProtocols" : [
      "BaseTargetType"
    ],
    "F_location" : "FollowingAPI.swift - Line: 16, Column: 1",
    "G_members" : [
      {
        "A_name" : "path",
        "B_kind" : "variable",
        "C_accessLevel" : "public",
        "D_attributes" : [

        ],
        "F_location" : "FollowingAPI.swift - Line: 17, Column: 5",
        "H_initialValue" : ""
      },
      {
        "A_name" : "method",
        "B_kind" : "variable",
        "C_accessLevel" : "public",
        "D_attributes" : [

        ],
        "F_location" : "FollowingAPI.swift - Line: 24, Column: 5",
        "H_initialValue" : ""
      },
      {
        "A_name" : "task",
        "B_kind" : "variable",
        "C_accessLevel" : "public",
        "D_attributes" : [

        ],
        "F_location" : "FollowingAPI.swift - Line: 33, Column: 5",
        "H_initialValue" : ""
      }
    ]
  },
  {
    "A_name" : "path",
    "B_kind" : "variable",
    "C_accessLevel" : "public",
    "D_attributes" : [

    ],
    "F_location" : "FollowingAPI.swift - Line: 17, Column: 5",
    "H_initialValue" : ""
  },
  {
    "A_name" : "method",
    "B_kind" : "variable",
    "C_accessLevel" : "public",
    "D_attributes" : [

    ],
    "F_location" : "FollowingAPI.swift - Line: 24, Column: 5",
    "H_initialValue" : ""
  },
  {
    "A_name" : "task",
    "B_kind" : "variable",
    "C_accessLevel" : "public",
    "D_attributes" : [

    ],
    "F_location" : "FollowingAPI.swift - Line: 33, Column: 5",
    "H_initialValue" : ""
  }
]