[
  {
    "A_name" : "DiaryDetailViewController",
    "B_kind" : "class",
    "C_accessLevel" : "public",
    "D_attributes" : [
      "final"
    ],
    "E_adoptedClassProtocols" : [
      "BaseUIViewController<DiaryDetailViewModel>"
    ],
    "F_location" : "DiaryDetailViewController.swift - Line: 13, Column: 1",
    "G_members" : [
      {
        "A_name" : "diaryId",
        "B_kind" : "variable",
        "C_accessLevel" : "internal",
        "D_attributes" : [

        ],
        "F_location" : "DiaryDetailViewController.swift - Line: 17, Column: 5",
        "H_initialValue" : ""
      },
      {
        "A_name" : "date",
        "B_kind" : "variable",
        "C_accessLevel" : "internal",
        "D_attributes" : [

        ],
        "F_location" : "DiaryDetailViewController.swift - Line: 18, Column: 5",
        "H_initialValue" : "\"\""
      },
      {
        "A_name" : "isPublished",
        "B_kind" : "variable",
        "C_accessLevel" : "private",
        "D_attributes" : [

        ],
        "F_location" : "DiaryDetailViewController.swift - Line: 19, Column: 5",
        "H_initialValue" : "true"
      },
      {
        "A_name" : "deleteTappedSubject",
        "B_kind" : "variable",
        "C_accessLevel" : "private",
        "D_attributes" : [

        ],
        "F_location" : "DiaryDetailViewController.swift - Line: 20, Column: 5",
        "H_initialValue" : "PassthroughSubject<Void, Never>()"
      },
      {
        "A_name" : "publishTappedSubject",
        "B_kind" : "variable",
        "C_accessLevel" : "private",
        "D_attributes" : [

        ],
        "F_location" : "DiaryDetailViewController.swift - Line: 21, Column: 5",
        "H_initialValue" : "PassthroughSubject<Void, Never>()"
      },
      {
        "A_name" : "unpublishTappedSubject",
        "B_kind" : "variable",
        "C_accessLevel" : "private",
        "D_attributes" : [

        ],
        "F_location" : "DiaryDetailViewController.swift - Line: 22, Column: 5",
        "H_initialValue" : "PassthroughSubject<Void, Never>()"
      },
      {
        "A_name" : "diaryDetailView",
        "B_kind" : "variable",
        "C_accessLevel" : "private",
        "D_attributes" : [

        ],
        "F_location" : "DiaryDetailViewController.swift - Line: 24, Column: 5",
        "H_initialValue" : "DiaryDetailView()"
      },
      {
        "A_name" : "isHighlightingEnabled",
        "B_kind" : "variable",
        "C_accessLevel" : "private",
        "D_attributes" : [

        ],
        "F_location" : "DiaryDetailViewController.swift - Line: 25, Column: 5",
        "H_initialValue" : "true"
      },
      {
        "A_name" : "dialog",
        "B_kind" : "variable",
        "C_accessLevel" : "private",
        "D_attributes" : [

        ],
        "F_location" : "DiaryDetailViewController.swift - Line: 26, Column: 5",
        "H_initialValue" : "Dialog()"
      },
      {
        "A_name" : "detailImage",
        "B_kind" : "variable",
        "C_accessLevel" : "private",
        "D_attributes" : [

        ],
        "F_location" : "DiaryDetailViewController.swift - Line: 27, Column: 5",
        "H_initialValue" : "DetailImageView(image: UIImage(resource: .imgLoadFailLargeIos))"
      },
      {
        "A_name" : "spacer",
        "B_kind" : "variable",
        "C_accessLevel" : "private",
        "D_attributes" : [

        ],
        "F_location" : "DiaryDetailViewController.swift - Line: 29, Column: 5",
        "H_initialValue" : "UIView()"
      },
      {
        "A_name" : "bottomSafeAreaBackgroundView",
        "B_kind" : "variable",
        "C_accessLevel" : "private",
        "D_attributes" : [

        ],
        "F_location" : "DiaryDetailViewController.swift - Line: 30, Column: 5",
        "H_initialValue" : "UIView()"
      },
      {
        "A_name" : "modal",
        "B_kind" : "variable",
        "C_accessLevel" : "internal",
        "D_attributes" : [

        ],
        "F_location" : "DiaryDetailViewController.swift - Line: 32, Column: 5",
        "H_initialValue" : "{\n        let modal = Modal()\n        modal.isHidden = true\n        return modal\n    }()"
      },
      {
        "A_name" : "button",
        "B_kind" : "variable",
        "C_accessLevel" : "private",
        "D_attributes" : [

        ],
        "F_location" : "DiaryDetailViewController.swift - Line: 38, Column: 5",
        "H_initialValue" : "{\n        let button = CTAButton(style: .TextButton(\"피드에 게시하기\"), autoBackground: true)\n        button.isEnabled = true\n        return button\n    }()"
      },
      {
        "A_name" : "feedbackViewController",
        "B_kind" : "variable",
        "C_accessLevel" : "private",
        "D_attributes" : [
          "lazy"
        ],
        "F_location" : "DiaryDetailViewController.swift - Line: 44, Column: 5",
        "H_initialValue" : "diContainer.makeFeedbackViewController(diaryId: diaryId)"
      },
      {
        "A_name" : "recommendedExpressionViewController",
        "B_kind" : "variable",
        "C_accessLevel" : "private",
        "D_attributes" : [
          "lazy"
        ],
        "F_location" : "DiaryDetailViewController.swift - Line: 45, Column: 5",
        "H_initialValue" : "diContainer.makeRecommendedExpressionViewController(diaryId: diaryId)"
      },
      {
        "A_name" : "segmentedControl",
        "B_kind" : "variable",
        "C_accessLevel" : "private",
        "D_attributes" : [

        ],
        "F_location" : "DiaryDetailViewController.swift - Line: 47, Column: 5",
        "H_initialValue" : ""
      },
      {
        "A_name" : "showsActionButton",
        "B_kind" : "variable",
        "C_accessLevel" : "public",
        "D_attributes" : [

        ],
        "F_location" : "DiaryDetailViewController.swift - Line: 49, Column: 5",
        "H_initialValue" : "true"
      },
      {
        "A_name" : "init",
        "B_kind" : "function",
        "C_accessLevel" : "public",
        "D_attributes" : [

        ],
        "F_location" : "DiaryDetailViewController.swift - Line: 53, Column: 5",
        "G_members" : [

        ],
        "I_parameterType" : [
          "DiaryDetailViewModel",
          "ViewControllerFactory",
          "Int"
        ],
        "I_parameters" : [
          "viewModel",
          "diContainer",
          "diaryId"
        ]
      },
      {
        "A_name" : "init",
        "B_kind" : "function",
        "C_accessLevel" : "required",
        "D_attributes" : [
          "required"
        ],
        "F_location" : "DiaryDetailViewController.swift - Line: 58, Column: 5",
        "G_members" : [

        ],
        "I_parameterType" : [
          "NSCoder"
        ],
        "I_parameters" : [
          "coder"
        ]
      },
      {
        "A_name" : "viewDidLoad",
        "B_kind" : "function",
        "C_accessLevel" : "public",
        "D_attributes" : [
          "override"
        ],
        "F_location" : "DiaryDetailViewController.swift - Line: 64, Column: 5",
        "G_members" : [

        ],
        "I_parameterType" : [

        ],
        "I_parameters" : [

        ]
      },
      {
        "A_name" : "viewWillAppear",
        "B_kind" : "function",
        "C_accessLevel" : "public",
        "D_attributes" : [
          "override"
        ],
        "F_location" : "DiaryDetailViewController.swift - Line: 97, Column: 5",
        "G_members" : [

        ],
        "I_parameterType" : [
          "Bool"
        ],
        "I_parameters" : [
          "_"
        ]
      },
      {
        "A_name" : "setUI",
        "B_kind" : "function",
        "C_accessLevel" : "public",
        "D_attributes" : [
          "override"
        ],
        "F_location" : "DiaryDetailViewController.swift - Line: 104, Column: 5",
        "G_members" : [

        ],
        "I_parameterType" : [

        ],
        "I_parameters" : [

        ]
      },
      {
        "A_name" : "setLayout",
        "B_kind" : "function",
        "C_accessLevel" : "public",
        "D_attributes" : [
          "override"
        ],
        "F_location" : "DiaryDetailViewController.swift - Line: 116, Column: 5",
        "G_members" : [

        ],
        "I_parameterType" : [

        ],
        "I_parameters" : [

        ]
      },
      {
        "A_name" : "bind",
        "B_kind" : "function",
        "C_accessLevel" : "public",
        "D_attributes" : [
          "override"
        ],
        "F_location" : "DiaryDetailViewController.swift - Line: 153, Column: 5",
        "G_members" : [
          {
            "A_name" : "input",
            "B_kind" : "variable",
            "C_accessLevel" : "internal",
            "D_attributes" : [

            ],
            "F_location" : "DiaryDetailViewController.swift - Line: 156, Column: 9",
            "H_initialValue" : "DiaryDetailViewModel.Input(\n            deleteTapped: deleteTappedSubject.eraseToAnyPublisher(),\n            publishTapped: publishTappedSubject.eraseToAnyPublisher(),\n            unpublishTapped: unpublishTappedSubject.eraseToAnyPublisher()\n        )"
          },
          {
            "A_name" : "output",
            "B_kind" : "variable",
            "C_accessLevel" : "internal",
            "D_attributes" : [

            ],
            "F_location" : "DiaryDetailViewController.swift - Line: 162, Column: 9",
            "H_initialValue" : "viewModel.transform(input: input)"
          }
        ],
        "I_parameterType" : [
          "DiaryDetailViewModel"
        ],
        "I_parameters" : [
          "viewModel"
        ]
      },
      {
        "A_name" : "navigationType",
        "B_kind" : "function",
        "C_accessLevel" : "public",
        "D_attributes" : [
          "override"
        ],
        "F_location" : "DiaryDetailViewController.swift - Line: 207, Column: 5",
        "G_members" : [

        ],
        "I_parameterType" : [

        ],
        "I_parameters" : [

        ],
        "J_returnType" : "-> NavigationType?"
      },
      {
        "A_name" : "backButtonTapped",
        "B_kind" : "function",
        "C_accessLevel" : "public",
        "D_attributes" : [
          "objc",
          "override"
        ],
        "F_location" : "DiaryDetailViewController.swift - Line: 211, Column: 5",
        "G_members" : [

        ],
        "I_parameterType" : [

        ],
        "I_parameters" : [

        ]
      },
      {
        "A_name" : "postButtonTapped",
        "B_kind" : "function",
        "C_accessLevel" : "private",
        "D_attributes" : [
          "objc"
        ],
        "F_location" : "DiaryDetailViewController.swift - Line: 215, Column: 5",
        "G_members" : [

        ],
        "I_parameterType" : [

        ],
        "I_parameters" : [

        ]
      },
      {
        "A_name" : "menuButtonTapped",
        "B_kind" : "function",
        "C_accessLevel" : "public",
        "D_attributes" : [
          "override"
        ],
        "F_location" : "DiaryDetailViewController.swift - Line: 225, Column: 5",
        "G_members" : [

        ],
        "I_parameterType" : [

        ],
        "I_parameters" : [

        ]
      },
      {
        "A_name" : "updateButtonTitle",
        "B_kind" : "function",
        "C_accessLevel" : "private",
        "D_attributes" : [

        ],
        "F_location" : "DiaryDetailViewController.swift - Line: 229, Column: 5",
        "G_members" : [
          {
            "A_name" : "title",
            "B_kind" : "variable",
            "C_accessLevel" : "internal",
            "D_attributes" : [

            ],
            "F_location" : "DiaryDetailViewController.swift - Line: 230, Column: 9",
            "H_initialValue" : "isPublished ? \"비공개하기\" : \"피드에 게시하기\""
          }
        ],
        "I_parameterType" : [

        ],
        "I_parameters" : [

        ]
      },
      {
        "A_name" : "showModal",
        "B_kind" : "function",
        "C_accessLevel" : "private",
        "D_attributes" : [
          "objc"
        ],
        "F_location" : "DiaryDetailViewController.swift - Line: 234, Column: 5",
        "G_members" : [

        ],
        "I_parameterType" : [

        ],
        "I_parameters" : [

        ]
      },
      {
        "A_name" : "showDeleteDialog",
        "B_kind" : "function",
        "C_accessLevel" : "private",
        "D_attributes" : [
          "objc"
        ],
        "F_location" : "DiaryDetailViewController.swift - Line: 257, Column: 5",
        "G_members" : [

        ],
        "I_parameterType" : [

        ],
        "I_parameters" : [

        ]
      },
      {
        "A_name" : "showReportDialog",
        "B_kind" : "function",
        "C_accessLevel" : "private",
        "D_attributes" : [
          "objc"
        ],
        "F_location" : "DiaryDetailViewController.swift - Line: 274, Column: 5",
        "G_members" : [

        ],
        "I_parameterType" : [

        ],
        "I_parameters" : [

        ]
      },
      {
        "A_name" : "showPostDialog",
        "B_kind" : "function",
        "C_accessLevel" : "private",
        "D_attributes" : [
          "objc"
        ],
        "F_location" : "DiaryDetailViewController.swift - Line: 293, Column: 5",
        "G_members" : [

        ],
        "I_parameterType" : [

        ],
        "I_parameters" : [

        ]
      },
      {
        "A_name" : "showPrivateDialog",
        "B_kind" : "function",
        "C_accessLevel" : "private",
        "D_attributes" : [
          "objc"
        ],
        "F_location" : "DiaryDetailViewController.swift - Line: 310, Column: 5",
        "G_members" : [

        ],
        "I_parameterType" : [

        ],
        "I_parameters" : [

        ]
      },
      {
        "A_name" : "showErrorDialog",
        "B_kind" : "function",
        "C_accessLevel" : "private",
        "D_attributes" : [

        ],
        "F_location" : "DiaryDetailViewController.swift - Line: 328, Column: 5",
        "G_members" : [

        ],
        "I_parameterType" : [
          "String"
        ],
        "I_parameters" : [
          "message"
        ]
      }
    ]
  },
  {
    "A_name" : "diaryId",
    "B_kind" : "variable",
    "C_accessLevel" : "internal",
    "D_attributes" : [

    ],
    "F_location" : "DiaryDetailViewController.swift - Line: 17, Column: 5",
    "H_initialValue" : ""
  },
  {
    "A_name" : "date",
    "B_kind" : "variable",
    "C_accessLevel" : "internal",
    "D_attributes" : [

    ],
    "F_location" : "DiaryDetailViewController.swift - Line: 18, Column: 5",
    "H_initialValue" : "\"\""
  },
  {
    "A_name" : "isPublished",
    "B_kind" : "variable",
    "C_accessLevel" : "private",
    "D_attributes" : [

    ],
    "F_location" : "DiaryDetailViewController.swift - Line: 19, Column: 5",
    "H_initialValue" : "true"
  },
  {
    "A_name" : "deleteTappedSubject",
    "B_kind" : "variable",
    "C_accessLevel" : "private",
    "D_attributes" : [

    ],
    "F_location" : "DiaryDetailViewController.swift - Line: 20, Column: 5",
    "H_initialValue" : "PassthroughSubject<Void, Never>()"
  },
  {
    "A_name" : "publishTappedSubject",
    "B_kind" : "variable",
    "C_accessLevel" : "private",
    "D_attributes" : [

    ],
    "F_location" : "DiaryDetailViewController.swift - Line: 21, Column: 5",
    "H_initialValue" : "PassthroughSubject<Void, Never>()"
  },
  {
    "A_name" : "unpublishTappedSubject",
    "B_kind" : "variable",
    "C_accessLevel" : "private",
    "D_attributes" : [

    ],
    "F_location" : "DiaryDetailViewController.swift - Line: 22, Column: 5",
    "H_initialValue" : "PassthroughSubject<Void, Never>()"
  },
  {
    "A_name" : "diaryDetailView",
    "B_kind" : "variable",
    "C_accessLevel" : "private",
    "D_attributes" : [

    ],
    "F_location" : "DiaryDetailViewController.swift - Line: 24, Column: 5",
    "H_initialValue" : "DiaryDetailView()"
  },
  {
    "A_name" : "isHighlightingEnabled",
    "B_kind" : "variable",
    "C_accessLevel" : "private",
    "D_attributes" : [

    ],
    "F_location" : "DiaryDetailViewController.swift - Line: 25, Column: 5",
    "H_initialValue" : "true"
  },
  {
    "A_name" : "dialog",
    "B_kind" : "variable",
    "C_accessLevel" : "private",
    "D_attributes" : [

    ],
    "F_location" : "DiaryDetailViewController.swift - Line: 26, Column: 5",
    "H_initialValue" : "Dialog()"
  },
  {
    "A_name" : "detailImage",
    "B_kind" : "variable",
    "C_accessLevel" : "private",
    "D_attributes" : [

    ],
    "F_location" : "DiaryDetailViewController.swift - Line: 27, Column: 5",
    "H_initialValue" : "DetailImageView(image: UIImage(resource: .imgLoadFailLargeIos))"
  },
  {
    "A_name" : "spacer",
    "B_kind" : "variable",
    "C_accessLevel" : "private",
    "D_attributes" : [

    ],
    "F_location" : "DiaryDetailViewController.swift - Line: 29, Column: 5",
    "H_initialValue" : "UIView()"
  },
  {
    "A_name" : "bottomSafeAreaBackgroundView",
    "B_kind" : "variable",
    "C_accessLevel" : "private",
    "D_attributes" : [

    ],
    "F_location" : "DiaryDetailViewController.swift - Line: 30, Column: 5",
    "H_initialValue" : "UIView()"
  },
  {
    "A_name" : "modal",
    "B_kind" : "variable",
    "C_accessLevel" : "internal",
    "D_attributes" : [

    ],
    "F_location" : "DiaryDetailViewController.swift - Line: 32, Column: 5",
    "H_initialValue" : "{\n        let modal = Modal()\n        modal.isHidden = true\n        return modal\n    }()"
  },
  {
    "A_name" : "modal",
    "B_kind" : "variable",
    "C_accessLevel" : "internal",
    "D_attributes" : [

    ],
    "F_location" : "DiaryDetailViewController.swift - Line: 33, Column: 9",
    "H_initialValue" : "Modal()"
  },
  {
    "A_name" : "button",
    "B_kind" : "variable",
    "C_accessLevel" : "private",
    "D_attributes" : [

    ],
    "F_location" : "DiaryDetailViewController.swift - Line: 38, Column: 5",
    "H_initialValue" : "{\n        let button = CTAButton(style: .TextButton(\"피드에 게시하기\"), autoBackground: true)\n        button.isEnabled = true\n        return button\n    }()"
  },
  {
    "A_name" : "button",
    "B_kind" : "variable",
    "C_accessLevel" : "internal",
    "D_attributes" : [

    ],
    "F_location" : "DiaryDetailViewController.swift - Line: 39, Column: 9",
    "H_initialValue" : "CTAButton(style: .TextButton(\"피드에 게시하기\"), autoBackground: true)"
  },
  {
    "A_name" : "feedbackViewController",
    "B_kind" : "variable",
    "C_accessLevel" : "private",
    "D_attributes" : [
      "lazy"
    ],
    "F_location" : "DiaryDetailViewController.swift - Line: 44, Column: 5",
    "H_initialValue" : "diContainer.makeFeedbackViewController(diaryId: diaryId)"
  },
  {
    "A_name" : "recommendedExpressionViewController",
    "B_kind" : "variable",
    "C_accessLevel" : "private",
    "D_attributes" : [
      "lazy"
    ],
    "F_location" : "DiaryDetailViewController.swift - Line: 45, Column: 5",
    "H_initialValue" : "diContainer.makeRecommendedExpressionViewController(diaryId: diaryId)"
  },
  {
    "A_name" : "segmentedControl",
    "B_kind" : "variable",
    "C_accessLevel" : "private",
    "D_attributes" : [

    ],
    "F_location" : "DiaryDetailViewController.swift - Line: 47, Column: 5",
    "H_initialValue" : ""
  },
  {
    "A_name" : "showsActionButton",
    "B_kind" : "variable",
    "C_accessLevel" : "public",
    "D_attributes" : [

    ],
    "F_location" : "DiaryDetailViewController.swift - Line: 49, Column: 5",
    "H_initialValue" : "true"
  },
  {
    "A_name" : "init",
    "B_kind" : "function",
    "C_accessLevel" : "public",
    "D_attributes" : [

    ],
    "F_location" : "DiaryDetailViewController.swift - Line: 53, Column: 5",
    "G_members" : [

    ],
    "I_parameterType" : [
      "DiaryDetailViewModel",
      "ViewControllerFactory",
      "Int"
    ],
    "I_parameters" : [
      "viewModel",
      "diContainer",
      "diaryId"
    ]
  },
  {
    "A_name" : "init",
    "B_kind" : "function",
    "C_accessLevel" : "required",
    "D_attributes" : [
      "required"
    ],
    "F_location" : "DiaryDetailViewController.swift - Line: 58, Column: 5",
    "G_members" : [

    ],
    "I_parameterType" : [
      "NSCoder"
    ],
    "I_parameters" : [
      "coder"
    ]
  },
  {
    "A_name" : "viewDidLoad",
    "B_kind" : "function",
    "C_accessLevel" : "public",
    "D_attributes" : [
      "override"
    ],
    "F_location" : "DiaryDetailViewController.swift - Line: 64, Column: 5",
    "G_members" : [

    ],
    "I_parameterType" : [

    ],
    "I_parameters" : [

    ]
  },
  {
    "A_name" : "viewWillAppear",
    "B_kind" : "function",
    "C_accessLevel" : "public",
    "D_attributes" : [
      "override"
    ],
    "F_location" : "DiaryDetailViewController.swift - Line: 97, Column: 5",
    "G_members" : [

    ],
    "I_parameterType" : [
      "Bool"
    ],
    "I_parameters" : [
      "_"
    ]
  },
  {
    "A_name" : "setUI",
    "B_kind" : "function",
    "C_accessLevel" : "public",
    "D_attributes" : [
      "override"
    ],
    "F_location" : "DiaryDetailViewController.swift - Line: 104, Column: 5",
    "G_members" : [

    ],
    "I_parameterType" : [

    ],
    "I_parameters" : [

    ]
  },
  {
    "A_name" : "setLayout",
    "B_kind" : "function",
    "C_accessLevel" : "public",
    "D_attributes" : [
      "override"
    ],
    "F_location" : "DiaryDetailViewController.swift - Line: 116, Column: 5",
    "G_members" : [

    ],
    "I_parameterType" : [

    ],
    "I_parameters" : [

    ]
  },
  {
    "A_name" : "bind",
    "B_kind" : "function",
    "C_accessLevel" : "public",
    "D_attributes" : [
      "override"
    ],
    "F_location" : "DiaryDetailViewController.swift - Line: 153, Column: 5",
    "G_members" : [
      {
        "A_name" : "input",
        "B_kind" : "variable",
        "C_accessLevel" : "internal",
        "D_attributes" : [

        ],
        "F_location" : "DiaryDetailViewController.swift - Line: 156, Column: 9",
        "H_initialValue" : "DiaryDetailViewModel.Input(\n            deleteTapped: deleteTappedSubject.eraseToAnyPublisher(),\n            publishTapped: publishTappedSubject.eraseToAnyPublisher(),\n            unpublishTapped: unpublishTappedSubject.eraseToAnyPublisher()\n        )"
      },
      {
        "A_name" : "output",
        "B_kind" : "variable",
        "C_accessLevel" : "internal",
        "D_attributes" : [

        ],
        "F_location" : "DiaryDetailViewController.swift - Line: 162, Column: 9",
        "H_initialValue" : "viewModel.transform(input: input)"
      }
    ],
    "I_parameterType" : [
      "DiaryDetailViewModel"
    ],
    "I_parameters" : [
      "viewModel"
    ]
  },
  {
    "A_name" : "input",
    "B_kind" : "variable",
    "C_accessLevel" : "internal",
    "D_attributes" : [

    ],
    "F_location" : "DiaryDetailViewController.swift - Line: 156, Column: 9",
    "H_initialValue" : "DiaryDetailViewModel.Input(\n            deleteTapped: deleteTappedSubject.eraseToAnyPublisher(),\n            publishTapped: publishTappedSubject.eraseToAnyPublisher(),\n            unpublishTapped: unpublishTappedSubject.eraseToAnyPublisher()\n        )"
  },
  {
    "A_name" : "output",
    "B_kind" : "variable",
    "C_accessLevel" : "internal",
    "D_attributes" : [

    ],
    "F_location" : "DiaryDetailViewController.swift - Line: 162, Column: 9",
    "H_initialValue" : "viewModel.transform(input: input)"
  },
  {
    "A_name" : "toast",
    "B_kind" : "variable",
    "C_accessLevel" : "internal",
    "D_attributes" : [

    ],
    "F_location" : "DiaryDetailViewController.swift - Line: 171, Column: 25",
    "H_initialValue" : "ToastMessage()"
  },
  {
    "A_name" : "toast",
    "B_kind" : "variable",
    "C_accessLevel" : "internal",
    "D_attributes" : [

    ],
    "F_location" : "DiaryDetailViewController.swift - Line: 184, Column: 17",
    "H_initialValue" : "ToastMessage()"
  },
  {
    "A_name" : "navigationType",
    "B_kind" : "function",
    "C_accessLevel" : "public",
    "D_attributes" : [
      "override"
    ],
    "F_location" : "DiaryDetailViewController.swift - Line: 207, Column: 5",
    "G_members" : [

    ],
    "I_parameterType" : [

    ],
    "I_parameters" : [

    ],
    "J_returnType" : "-> NavigationType?"
  },
  {
    "A_name" : "backButtonTapped",
    "B_kind" : "function",
    "C_accessLevel" : "public",
    "D_attributes" : [
      "objc",
      "override"
    ],
    "F_location" : "DiaryDetailViewController.swift - Line: 211, Column: 5",
    "G_members" : [

    ],
    "I_parameterType" : [

    ],
    "I_parameters" : [

    ]
  },
  {
    "A_name" : "postButtonTapped",
    "B_kind" : "function",
    "C_accessLevel" : "private",
    "D_attributes" : [
      "objc"
    ],
    "F_location" : "DiaryDetailViewController.swift - Line: 215, Column: 5",
    "G_members" : [

    ],
    "I_parameterType" : [

    ],
    "I_parameters" : [

    ]
  },
  {
    "A_name" : "menuButtonTapped",
    "B_kind" : "function",
    "C_accessLevel" : "public",
    "D_attributes" : [
      "override"
    ],
    "F_location" : "DiaryDetailViewController.swift - Line: 225, Column: 5",
    "G_members" : [

    ],
    "I_parameterType" : [

    ],
    "I_parameters" : [

    ]
  },
  {
    "A_name" : "updateButtonTitle",
    "B_kind" : "function",
    "C_accessLevel" : "private",
    "D_attributes" : [

    ],
    "F_location" : "DiaryDetailViewController.swift - Line: 229, Column: 5",
    "G_members" : [
      {
        "A_name" : "title",
        "B_kind" : "variable",
        "C_accessLevel" : "internal",
        "D_attributes" : [

        ],
        "F_location" : "DiaryDetailViewController.swift - Line: 230, Column: 9",
        "H_initialValue" : "isPublished ? \"비공개하기\" : \"피드에 게시하기\""
      }
    ],
    "I_parameterType" : [

    ],
    "I_parameters" : [

    ]
  },
  {
    "A_name" : "title",
    "B_kind" : "variable",
    "C_accessLevel" : "internal",
    "D_attributes" : [

    ],
    "F_location" : "DiaryDetailViewController.swift - Line: 230, Column: 9",
    "H_initialValue" : "isPublished ? \"비공개하기\" : \"피드에 게시하기\""
  },
  {
    "A_name" : "showModal",
    "B_kind" : "function",
    "C_accessLevel" : "private",
    "D_attributes" : [
      "objc"
    ],
    "F_location" : "DiaryDetailViewController.swift - Line: 234, Column: 5",
    "G_members" : [

    ],
    "I_parameterType" : [

    ],
    "I_parameters" : [

    ]
  },
  {
    "A_name" : "showDeleteDialog",
    "B_kind" : "function",
    "C_accessLevel" : "private",
    "D_attributes" : [
      "objc"
    ],
    "F_location" : "DiaryDetailViewController.swift - Line: 257, Column: 5",
    "G_members" : [

    ],
    "I_parameterType" : [

    ],
    "I_parameters" : [

    ]
  },
  {
    "A_name" : "showReportDialog",
    "B_kind" : "function",
    "C_accessLevel" : "private",
    "D_attributes" : [
      "objc"
    ],
    "F_location" : "DiaryDetailViewController.swift - Line: 274, Column: 5",
    "G_members" : [

    ],
    "I_parameterType" : [

    ],
    "I_parameters" : [

    ]
  },
  {
    "A_name" : "safariVC",
    "B_kind" : "variable",
    "C_accessLevel" : "internal",
    "D_attributes" : [

    ],
    "F_location" : "DiaryDetailViewController.swift - Line: 286, Column: 17",
    "H_initialValue" : "SFSafariViewController(url: url)"
  },
  {
    "A_name" : "showPostDialog",
    "B_kind" : "function",
    "C_accessLevel" : "private",
    "D_attributes" : [
      "objc"
    ],
    "F_location" : "DiaryDetailViewController.swift - Line: 293, Column: 5",
    "G_members" : [

    ],
    "I_parameterType" : [

    ],
    "I_parameters" : [

    ]
  },
  {
    "A_name" : "showPrivateDialog",
    "B_kind" : "function",
    "C_accessLevel" : "private",
    "D_attributes" : [
      "objc"
    ],
    "F_location" : "DiaryDetailViewController.swift - Line: 310, Column: 5",
    "G_members" : [

    ],
    "I_parameterType" : [

    ],
    "I_parameters" : [

    ]
  },
  {
    "A_name" : "showErrorDialog",
    "B_kind" : "function",
    "C_accessLevel" : "private",
    "D_attributes" : [

    ],
    "F_location" : "DiaryDetailViewController.swift - Line: 328, Column: 5",
    "G_members" : [

    ],
    "I_parameterType" : [
      "String"
    ],
    "I_parameters" : [
      "message"
    ]
  }
]