[
  {
    "A_name" : "DiaryWritingEntity",
    "B_kind" : "struct",
    "C_accessLevel" : "public",
    "D_attributes" : [

    ],
    "E_adoptedClassProtocols" : [

    ],
    "F_location" : "DiaryWritingEntity.swift - Line: 10, Column: 1",
    "G_members" : [
      {
        "A_name" : "originalText",
        "B_kind" : "variable",
        "C_accessLevel" : "public",
        "D_attributes" : [

        ],
        "F_location" : "DiaryWritingEntity.swift - Line: 11, Column: 5",
        "H_initialValue" : ""
      },
      {
        "A_name" : "date",
        "B_kind" : "variable",
        "C_accessLevel" : "public",
        "D_attributes" : [

        ],
        "F_location" : "DiaryWritingEntity.swift - Line: 12, Column: 5",
        "H_initialValue" : ""
      },
      {
        "A_name" : "image",
        "B_kind" : "variable",
        "C_accessLevel" : "public",
        "D_attributes" : [

        ],
        "F_location" : "DiaryWritingEntity.swift - Line: 13, Column: 5",
        "H_initialValue" : ""
      },
      {
        "A_name" : "init",
        "B_kind" : "function",
        "C_accessLevel" : "public",
        "D_attributes" : [

        ],
        "F_location" : "DiaryWritingEntity.swift - Line: 15, Column: 5",
        "G_members" : [

        ],
        "I_parameterType" : [
          "String",
          "String",
          "String?"
        ],
        "I_parameters" : [
          "originalText",
          "date",
          "fileKey"
        ]
      },
      {
        "A_name" : "ImageFile",
        "B_kind" : "struct",
        "C_accessLevel" : "public",
        "D_attributes" : [

        ],
        "E_adoptedClassProtocols" : [

        ],
        "F_location" : "DiaryWritingEntity.swift - Line: 21, Column: 5",
        "G_members" : [
          {
            "A_name" : "fileKey",
            "B_kind" : "variable",
            "C_accessLevel" : "public",
            "D_attributes" : [

            ],
            "F_location" : "DiaryWritingEntity.swift - Line: 22, Column: 9",
            "H_initialValue" : ""
          },
          {
            "A_name" : "purpose",
            "B_kind" : "variable",
            "C_accessLevel" : "public",
            "D_attributes" : [

            ],
            "F_location" : "DiaryWritingEntity.swift - Line: 23, Column: 9",
            "H_initialValue" : ""
          },
          {
            "A_name" : "init",
            "B_kind" : "function",
            "C_accessLevel" : "public",
            "D_attributes" : [

            ],
            "F_location" : "DiaryWritingEntity.swift - Line: 25, Column: 9",
            "G_members" : [

            ],
            "I_parameterType" : [
              "String",
              "String"
            ],
            "I_parameters" : [
              "fileKey",
              "purpose"
            ]
          }
        ]
      }
    ]
  },
  {
    "A_name" : "originalText",
    "B_kind" : "variable",
    "C_accessLevel" : "public",
    "D_attributes" : [

    ],
    "F_location" : "DiaryWritingEntity.swift - Line: 11, Column: 5",
    "H_initialValue" : ""
  },
  {
    "A_name" : "date",
    "B_kind" : "variable",
    "C_accessLevel" : "public",
    "D_attributes" : [

    ],
    "F_location" : "DiaryWritingEntity.swift - Line: 12, Column: 5",
    "H_initialValue" : ""
  },
  {
    "A_name" : "image",
    "B_kind" : "variable",
    "C_accessLevel" : "public",
    "D_attributes" : [

    ],
    "F_location" : "DiaryWritingEntity.swift - Line: 13, Column: 5",
    "H_initialValue" : ""
  },
  {
    "A_name" : "init",
    "B_kind" : "function",
    "C_accessLevel" : "public",
    "D_attributes" : [

    ],
    "F_location" : "DiaryWritingEntity.swift - Line: 15, Column: 5",
    "G_members" : [

    ],
    "I_parameterType" : [
      "String",
      "String",
      "String?"
    ],
    "I_parameters" : [
      "originalText",
      "date",
      "fileKey"
    ]
  },
  {
    "A_name" : "ImageFile",
    "B_kind" : "struct",
    "C_accessLevel" : "public",
    "D_attributes" : [

    ],
    "E_adoptedClassProtocols" : [

    ],
    "F_location" : "DiaryWritingEntity.swift - Line: 21, Column: 5",
    "G_members" : [
      {
        "A_name" : "fileKey",
        "B_kind" : "variable",
        "C_accessLevel" : "public",
        "D_attributes" : [

        ],
        "F_location" : "DiaryWritingEntity.swift - Line: 22, Column: 9",
        "H_initialValue" : ""
      },
      {
        "A_name" : "purpose",
        "B_kind" : "variable",
        "C_accessLevel" : "public",
        "D_attributes" : [

        ],
        "F_location" : "DiaryWritingEntity.swift - Line: 23, Column: 9",
        "H_initialValue" : ""
      },
      {
        "A_name" : "init",
        "B_kind" : "function",
        "C_accessLevel" : "public",
        "D_attributes" : [

        ],
        "F_location" : "DiaryWritingEntity.swift - Line: 25, Column: 9",
        "G_members" : [

        ],
        "I_parameterType" : [
          "String",
          "String"
        ],
        "I_parameters" : [
          "fileKey",
          "purpose"
        ]
      }
    ]
  },
  {
    "A_name" : "fileKey",
    "B_kind" : "variable",
    "C_accessLevel" : "public",
    "D_attributes" : [

    ],
    "F_location" : "DiaryWritingEntity.swift - Line: 22, Column: 9",
    "H_initialValue" : ""
  },
  {
    "A_name" : "purpose",
    "B_kind" : "variable",
    "C_accessLevel" : "public",
    "D_attributes" : [

    ],
    "F_location" : "DiaryWritingEntity.swift - Line: 23, Column: 9",
    "H_initialValue" : ""
  },
  {
    "A_name" : "init",
    "B_kind" : "function",
    "C_accessLevel" : "public",
    "D_attributes" : [

    ],
    "F_location" : "DiaryWritingEntity.swift - Line: 25, Column: 9",
    "G_members" : [

    ],
    "I_parameterType" : [
      "String",
      "String"
    ],
    "I_parameters" : [
      "fileKey",
      "purpose"
    ]
  },
  {
    "A_name" : "DiaryWritingResponseEntity",
    "B_kind" : "struct",
    "C_accessLevel" : "public",
    "D_attributes" : [

    ],
    "E_adoptedClassProtocols" : [

    ],
    "F_location" : "DiaryWritingEntity.swift - Line: 32, Column: 1",
    "G_members" : [
      {
        "A_name" : "diaryId",
        "B_kind" : "variable",
        "C_accessLevel" : "public",
        "D_attributes" : [

        ],
        "F_location" : "DiaryWritingEntity.swift - Line: 33, Column: 5",
        "H_initialValue" : ""
      },
      {
        "A_name" : "init",
        "B_kind" : "function",
        "C_accessLevel" : "public",
        "D_attributes" : [

        ],
        "F_location" : "DiaryWritingEntity.swift - Line: 35, Column: 5",
        "G_members" : [

        ],
        "I_parameterType" : [
          "Int"
        ],
        "I_parameters" : [
          "diaryId"
        ]
      }
    ]
  },
  {
    "A_name" : "diaryId",
    "B_kind" : "variable",
    "C_accessLevel" : "public",
    "D_attributes" : [

    ],
    "F_location" : "DiaryWritingEntity.swift - Line: 33, Column: 5",
    "H_initialValue" : ""
  },
  {
    "A_name" : "init",
    "B_kind" : "function",
    "C_accessLevel" : "public",
    "D_attributes" : [

    ],
    "F_location" : "DiaryWritingEntity.swift - Line: 35, Column: 5",
    "G_members" : [

    ],
    "I_parameterType" : [
      "Int"
    ],
    "I_parameters" : [
      "diaryId"
    ]
  }
]