[
  {
    "A_name" : "ProfileEntity",
    "B_kind" : "struct",
    "C_accessLevel" : "public",
    "D_attributes" : [

    ],
    "E_adoptedClassProtocols" : [

    ],
    "F_location" : "ProfileEntity.swift - Line: 8, Column: 1",
    "G_members" : [
      {
        "A_name" : "nickname",
        "B_kind" : "variable",
        "C_accessLevel" : "public",
        "D_attributes" : [

        ],
        "F_location" : "ProfileEntity.swift - Line: 9, Column: 5",
        "H_initialValue" : ""
      },
      {
        "A_name" : "adAlarmAgree",
        "B_kind" : "variable",
        "C_accessLevel" : "public",
        "D_attributes" : [

        ],
        "F_location" : "ProfileEntity.swift - Line: 10, Column: 5",
        "H_initialValue" : ""
      },
      {
        "A_name" : "image",
        "B_kind" : "variable",
        "C_accessLevel" : "public",
        "D_attributes" : [

        ],
        "F_location" : "ProfileEntity.swift - Line: 11, Column: 5",
        "H_initialValue" : ""
      },
      {
        "A_name" : "init",
        "B_kind" : "function",
        "C_accessLevel" : "public",
        "D_attributes" : [

        ],
        "F_location" : "ProfileEntity.swift - Line: 13, Column: 5",
        "G_members" : [

        ],
        "I_parameterType" : [
          "String",
          "Bool",
          "String?"
        ],
        "I_parameters" : [
          "nickname",
          "adAlarmAgree",
          "fileKey"
        ]
      },
      {
        "A_name" : "ImageFile",
        "B_kind" : "struct",
        "C_accessLevel" : "public",
        "D_attributes" : [

        ],
        "E_adoptedClassProtocols" : [

        ],
        "F_location" : "ProfileEntity.swift - Line: 19, Column: 5",
        "G_members" : [
          {
            "A_name" : "fileKey",
            "B_kind" : "variable",
            "C_accessLevel" : "public",
            "D_attributes" : [

            ],
            "F_location" : "ProfileEntity.swift - Line: 20, Column: 9",
            "H_initialValue" : ""
          },
          {
            "A_name" : "purpose",
            "B_kind" : "variable",
            "C_accessLevel" : "public",
            "D_attributes" : [

            ],
            "F_location" : "ProfileEntity.swift - Line: 21, Column: 9",
            "H_initialValue" : ""
          },
          {
            "A_name" : "init",
            "B_kind" : "function",
            "C_accessLevel" : "public",
            "D_attributes" : [

            ],
            "F_location" : "ProfileEntity.swift - Line: 23, Column: 9",
            "G_members" : [

            ],
            "I_parameterType" : [
              "String",
              "String"
            ],
            "I_parameters" : [
              "fileKey",
              "purpose"
            ]
          }
        ]
      }
    ]
  },
  {
    "A_name" : "nickname",
    "B_kind" : "variable",
    "C_accessLevel" : "public",
    "D_attributes" : [

    ],
    "F_location" : "ProfileEntity.swift - Line: 9, Column: 5",
    "H_initialValue" : ""
  },
  {
    "A_name" : "adAlarmAgree",
    "B_kind" : "variable",
    "C_accessLevel" : "public",
    "D_attributes" : [

    ],
    "F_location" : "ProfileEntity.swift - Line: 10, Column: 5",
    "H_initialValue" : ""
  },
  {
    "A_name" : "image",
    "B_kind" : "variable",
    "C_accessLevel" : "public",
    "D_attributes" : [

    ],
    "F_location" : "ProfileEntity.swift - Line: 11, Column: 5",
    "H_initialValue" : ""
  },
  {
    "A_name" : "init",
    "B_kind" : "function",
    "C_accessLevel" : "public",
    "D_attributes" : [

    ],
    "F_location" : "ProfileEntity.swift - Line: 13, Column: 5",
    "G_members" : [

    ],
    "I_parameterType" : [
      "String",
      "Bool",
      "String?"
    ],
    "I_parameters" : [
      "nickname",
      "adAlarmAgree",
      "fileKey"
    ]
  },
  {
    "A_name" : "ImageFile",
    "B_kind" : "struct",
    "C_accessLevel" : "public",
    "D_attributes" : [

    ],
    "E_adoptedClassProtocols" : [

    ],
    "F_location" : "ProfileEntity.swift - Line: 19, Column: 5",
    "G_members" : [
      {
        "A_name" : "fileKey",
        "B_kind" : "variable",
        "C_accessLevel" : "public",
        "D_attributes" : [

        ],
        "F_location" : "ProfileEntity.swift - Line: 20, Column: 9",
        "H_initialValue" : ""
      },
      {
        "A_name" : "purpose",
        "B_kind" : "variable",
        "C_accessLevel" : "public",
        "D_attributes" : [

        ],
        "F_location" : "ProfileEntity.swift - Line: 21, Column: 9",
        "H_initialValue" : ""
      },
      {
        "A_name" : "init",
        "B_kind" : "function",
        "C_accessLevel" : "public",
        "D_attributes" : [

        ],
        "F_location" : "ProfileEntity.swift - Line: 23, Column: 9",
        "G_members" : [

        ],
        "I_parameterType" : [
          "String",
          "String"
        ],
        "I_parameters" : [
          "fileKey",
          "purpose"
        ]
      }
    ]
  },
  {
    "A_name" : "fileKey",
    "B_kind" : "variable",
    "C_accessLevel" : "public",
    "D_attributes" : [

    ],
    "F_location" : "ProfileEntity.swift - Line: 20, Column: 9",
    "H_initialValue" : ""
  },
  {
    "A_name" : "purpose",
    "B_kind" : "variable",
    "C_accessLevel" : "public",
    "D_attributes" : [

    ],
    "F_location" : "ProfileEntity.swift - Line: 21, Column: 9",
    "H_initialValue" : ""
  },
  {
    "A_name" : "init",
    "B_kind" : "function",
    "C_accessLevel" : "public",
    "D_attributes" : [

    ],
    "F_location" : "ProfileEntity.swift - Line: 23, Column: 9",
    "G_members" : [

    ],
    "I_parameterType" : [
      "String",
      "String"
    ],
    "I_parameters" : [
      "fileKey",
      "purpose"
    ]
  }
]