[
  {
    "A_name" : "Thread",
    "B_kind" : "extension",
    "C_accessLevel" : "private",
    "D_attributes" : [

    ],
    "E_adoptedClassProtocols" : [

    ],
    "F_location" : "SchedulerSpec.swift - Line: 20, Column: 2",
    "G_members" : [
      {
        "A_name" : "isMainThread",
        "B_kind" : "variable",
        "C_accessLevel" : "static",
        "D_attributes" : [
          "static"
        ],
        "F_location" : "SchedulerSpec.swift - Line: 22, Column: 3",
        "H_initialValue" : ""
      }
    ]
  },
  {
    "A_name" : "isMainThread",
    "B_kind" : "variable",
    "C_accessLevel" : "static",
    "D_attributes" : [
      "static"
    ],
    "F_location" : "SchedulerSpec.swift - Line: 22, Column: 3",
    "H_initialValue" : ""
  },
  {
    "A_name" : "SchedulerSpec",
    "B_kind" : "class",
    "C_accessLevel" : "internal",
    "D_attributes" : [

    ],
    "E_adoptedClassProtocols" : [
      "QuickSpec"
    ],
    "F_location" : "SchedulerSpec.swift - Line: 28, Column: 1",
    "G_members" : [
      {
        "A_name" : "spec",
        "B_kind" : "function",
        "C_accessLevel" : "override",
        "D_attributes" : [
          "override"
        ],
        "F_location" : "SchedulerSpec.swift - Line: 29, Column: 2",
        "G_members" : [

        ],
        "I_parameterType" : [

        ],
        "I_parameters" : [

        ]
      }
    ]
  },
  {
    "A_name" : "spec",
    "B_kind" : "function",
    "C_accessLevel" : "override",
    "D_attributes" : [
      "override"
    ],
    "F_location" : "SchedulerSpec.swift - Line: 29, Column: 2",
    "G_members" : [

    ],
    "I_parameterType" : [

    ],
    "I_parameters" : [

    ]
  },
  {
    "A_name" : "didRun",
    "B_kind" : "variable",
    "C_accessLevel" : "internal",
    "D_attributes" : [

    ],
    "F_location" : "SchedulerSpec.swift - Line: 32, Column: 5",
    "H_initialValue" : "false"
  },
  {
    "A_name" : "dispatchSyncInBackground",
    "B_kind" : "function",
    "C_accessLevel" : "internal",
    "D_attributes" : [

    ],
    "F_location" : "SchedulerSpec.swift - Line: 42, Column: 4",
    "G_members" : [
      {
        "A_name" : "group",
        "B_kind" : "variable",
        "C_accessLevel" : "internal",
        "D_attributes" : [

        ],
        "F_location" : "SchedulerSpec.swift - Line: 43, Column: 5",
        "H_initialValue" : "DispatchGroup()"
      },
      {
        "A_name" : "globalQueue",
        "B_kind" : "variable",
        "C_accessLevel" : "internal",
        "D_attributes" : [

        ],
        "F_location" : "SchedulerSpec.swift - Line: 45, Column: 5",
        "H_initialValue" : ""
      }
    ],
    "I_parameterType" : [
      "@escaping () -> Void"
    ],
    "I_parameters" : [
      "_"
    ]
  },
  {
    "A_name" : "group",
    "B_kind" : "variable",
    "C_accessLevel" : "internal",
    "D_attributes" : [

    ],
    "F_location" : "SchedulerSpec.swift - Line: 43, Column: 5",
    "H_initialValue" : "DispatchGroup()"
  },
  {
    "A_name" : "globalQueue",
    "B_kind" : "variable",
    "C_accessLevel" : "internal",
    "D_attributes" : [

    ],
    "F_location" : "SchedulerSpec.swift - Line: 45, Column: 5",
    "H_initialValue" : ""
  },
  {
    "A_name" : "scheduler",
    "B_kind" : "variable",
    "C_accessLevel" : "internal",
    "D_attributes" : [

    ],
    "F_location" : "SchedulerSpec.swift - Line: 57, Column: 5",
    "H_initialValue" : "UIScheduler()"
  },
  {
    "A_name" : "values",
    "B_kind" : "variable",
    "C_accessLevel" : "internal",
    "D_attributes" : [

    ],
    "F_location" : "SchedulerSpec.swift - Line: 58, Column: 5",
    "H_initialValue" : "[]"
  },
  {
    "A_name" : "scheduler",
    "B_kind" : "variable",
    "C_accessLevel" : "internal",
    "D_attributes" : [

    ],
    "F_location" : "SchedulerSpec.swift - Line: 79, Column: 5",
    "H_initialValue" : "UIScheduler()"
  },
  {
    "A_name" : "values",
    "B_kind" : "variable",
    "C_accessLevel" : "internal",
    "D_attributes" : [

    ],
    "F_location" : "SchedulerSpec.swift - Line: 80, Column: 5",
    "H_initialValue" : "[]"
  },
  {
    "A_name" : "scheduler",
    "B_kind" : "variable",
    "C_accessLevel" : "internal",
    "D_attributes" : [

    ],
    "F_location" : "SchedulerSpec.swift - Line: 113, Column: 5",
    "H_initialValue" : "UIScheduler()"
  },
  {
    "A_name" : "values",
    "B_kind" : "variable",
    "C_accessLevel" : "internal",
    "D_attributes" : [

    ],
    "F_location" : "SchedulerSpec.swift - Line: 114, Column: 5",
    "H_initialValue" : "[]"
  },
  {
    "A_name" : "didRun",
    "B_kind" : "variable",
    "C_accessLevel" : "internal",
    "D_attributes" : [

    ],
    "F_location" : "SchedulerSpec.swift - Line: 142, Column: 5",
    "H_initialValue" : "false"
  },
  {
    "A_name" : "scheduler",
    "B_kind" : "variable",
    "C_accessLevel" : "internal",
    "D_attributes" : [

    ],
    "F_location" : "SchedulerSpec.swift - Line: 143, Column: 5",
    "H_initialValue" : "QueueScheduler.makeForTesting()"
  },
  {
    "A_name" : "scheduler",
    "B_kind" : "variable",
    "C_accessLevel" : "internal",
    "D_attributes" : [

    ],
    "F_location" : "SchedulerSpec.swift - Line: 154, Column: 5",
    "H_initialValue" : ""
  },
  {
    "A_name" : "value",
    "B_kind" : "variable",
    "C_accessLevel" : "internal",
    "D_attributes" : [

    ],
    "F_location" : "SchedulerSpec.swift - Line: 162, Column: 6",
    "H_initialValue" : "0"
  },
  {
    "A_name" : "didRun",
    "B_kind" : "variable",
    "C_accessLevel" : "internal",
    "D_attributes" : [

    ],
    "F_location" : "SchedulerSpec.swift - Line: 178, Column: 6",
    "H_initialValue" : "false"
  },
  {
    "A_name" : "disposable",
    "B_kind" : "variable",
    "C_accessLevel" : "internal",
    "D_attributes" : [

    ],
    "F_location" : "SchedulerSpec.swift - Line: 191, Column: 6",
    "H_initialValue" : "SerialDisposable()"
  },
  {
    "A_name" : "count",
    "B_kind" : "variable",
    "C_accessLevel" : "internal",
    "D_attributes" : [

    ],
    "F_location" : "SchedulerSpec.swift - Line: 193, Column: 6",
    "H_initialValue" : "0"
  },
  {
    "A_name" : "timesToRun",
    "B_kind" : "variable",
    "C_accessLevel" : "internal",
    "D_attributes" : [

    ],
    "F_location" : "SchedulerSpec.swift - Line: 194, Column: 6",
    "H_initialValue" : "3"
  },
  {
    "A_name" : "count",
    "B_kind" : "variable",
    "C_accessLevel" : "internal",
    "D_attributes" : [

    ],
    "F_location" : "SchedulerSpec.swift - Line: 213, Column: 6",
    "H_initialValue" : "0"
  },
  {
    "A_name" : "timesToIncrement",
    "B_kind" : "variable",
    "C_accessLevel" : "internal",
    "D_attributes" : [

    ],
    "F_location" : "SchedulerSpec.swift - Line: 214, Column: 6",
    "H_initialValue" : "3"
  },
  {
    "A_name" : "scheduleAndDeinitDisposable",
    "B_kind" : "function",
    "C_accessLevel" : "internal",
    "D_attributes" : [

    ],
    "F_location" : "SchedulerSpec.swift - Line: 217, Column: 6",
    "G_members" : [

    ],
    "I_parameterType" : [

    ],
    "I_parameters" : [

    ]
  },
  {
    "A_name" : "disposable1",
    "B_kind" : "variable",
    "C_accessLevel" : "internal",
    "D_attributes" : [

    ],
    "F_location" : "SchedulerSpec.swift - Line: 238, Column: 6",
    "H_initialValue" : "SerialDisposable()"
  },
  {
    "A_name" : "disposable2",
    "B_kind" : "variable",
    "C_accessLevel" : "internal",
    "D_attributes" : [

    ],
    "F_location" : "SchedulerSpec.swift - Line: 239, Column: 6",
    "H_initialValue" : "SerialDisposable()"
  },
  {
    "A_name" : "count",
    "B_kind" : "variable",
    "C_accessLevel" : "internal",
    "D_attributes" : [

    ],
    "F_location" : "SchedulerSpec.swift - Line: 241, Column: 6",
    "H_initialValue" : "0"
  },
  {
    "A_name" : "timesToRun",
    "B_kind" : "variable",
    "C_accessLevel" : "internal",
    "D_attributes" : [

    ],
    "F_location" : "SchedulerSpec.swift - Line: 242, Column: 6",
    "H_initialValue" : "3"
  },
  {
    "A_name" : "interval",
    "B_kind" : "variable",
    "C_accessLevel" : "internal",
    "D_attributes" : [

    ],
    "F_location" : "SchedulerSpec.swift - Line: 244, Column: 6",
    "H_initialValue" : "DispatchTimeInterval.milliseconds(10)"
  },
  {
    "A_name" : "scheduler",
    "B_kind" : "variable",
    "C_accessLevel" : "internal",
    "D_attributes" : [

    ],
    "F_location" : "SchedulerSpec.swift - Line: 274, Column: 4",
    "H_initialValue" : ""
  },
  {
    "A_name" : "startDate",
    "B_kind" : "variable",
    "C_accessLevel" : "internal",
    "D_attributes" : [

    ],
    "F_location" : "SchedulerSpec.swift - Line: 275, Column: 4",
    "H_initialValue" : ""
  },
  {
    "A_name" : "dateComparisonDelta",
    "B_kind" : "variable",
    "C_accessLevel" : "internal",
    "D_attributes" : [

    ],
    "F_location" : "SchedulerSpec.swift - Line: 278, Column: 4",
    "H_initialValue" : "0.00001"
  },
  {
    "A_name" : "string",
    "B_kind" : "variable",
    "C_accessLevel" : "internal",
    "D_attributes" : [

    ],
    "F_location" : "SchedulerSpec.swift - Line: 288, Column: 5",
    "H_initialValue" : "\"\""
  },
  {
    "A_name" : "string",
    "B_kind" : "variable",
    "C_accessLevel" : "internal",
    "D_attributes" : [

    ],
    "F_location" : "SchedulerSpec.swift - Line: 309, Column: 5",
    "H_initialValue" : "\"\""
  },
  {
    "A_name" : "string",
    "B_kind" : "variable",
    "C_accessLevel" : "internal",
    "D_attributes" : [

    ],
    "F_location" : "SchedulerSpec.swift - Line: 335, Column: 5",
    "H_initialValue" : "\"\""
  },
  {
    "A_name" : "schedulerB",
    "B_kind" : "variable",
    "C_accessLevel" : "internal",
    "D_attributes" : [

    ],
    "F_location" : "SchedulerSpec.swift - Line: 360, Column: 5",
    "H_initialValue" : "TestScheduler(startDate: startDate)"
  }
]