[
  {
    "A_name" : "MatcherFunc",
    "B_kind" : "struct",
    "C_accessLevel" : "public",
    "D_attributes" : [
      "available"
    ],
    "E_adoptedClassProtocols" : [
      "Matcher"
    ],
    "F_location" : "MatcherFunc.swift - Line: 12, Column: 1",
    "G_members" : [
      {
        "A_name" : "matcher",
        "B_kind" : "variable",
        "C_accessLevel" : "public",
        "D_attributes" : [

        ],
        "F_location" : "MatcherFunc.swift - Line: 14, Column: 5",
        "H_initialValue" : ""
      },
      {
        "A_name" : "init",
        "B_kind" : "function",
        "C_accessLevel" : "public",
        "D_attributes" : [

        ],
        "F_location" : "MatcherFunc.swift - Line: 16, Column: 5",
        "G_members" : [

        ],
        "I_parameterType" : [
          "@escaping (Expression<T>, FailureMessage) throws -> Bool"
        ],
        "I_parameters" : [
          "_"
        ]
      },
      {
        "A_name" : "matches",
        "B_kind" : "function",
        "C_accessLevel" : "public",
        "D_attributes" : [

        ],
        "F_location" : "MatcherFunc.swift - Line: 20, Column: 5",
        "G_members" : [

        ],
        "I_parameterType" : [
          "Expression<T>",
          "FailureMessage"
        ],
        "I_parameters" : [
          "_",
          "failureMessage"
        ],
        "J_returnType" : "-> Bool"
      },
      {
        "A_name" : "doesNotMatch",
        "B_kind" : "function",
        "C_accessLevel" : "public",
        "D_attributes" : [

        ],
        "F_location" : "MatcherFunc.swift - Line: 24, Column: 5",
        "G_members" : [

        ],
        "I_parameterType" : [
          "Expression<T>",
          "FailureMessage"
        ],
        "I_parameters" : [
          "_",
          "failureMessage"
        ],
        "J_returnType" : "-> Bool"
      },
      {
        "A_name" : "predicate",
        "B_kind" : "variable",
        "C_accessLevel" : "public",
        "D_attributes" : [
          "available"
        ],
        "F_location" : "MatcherFunc.swift - Line: 31, Column: 5",
        "H_initialValue" : ""
      }
    ]
  },
  {
    "A_name" : "matcher",
    "B_kind" : "variable",
    "C_accessLevel" : "public",
    "D_attributes" : [

    ],
    "F_location" : "MatcherFunc.swift - Line: 14, Column: 5",
    "H_initialValue" : ""
  },
  {
    "A_name" : "init",
    "B_kind" : "function",
    "C_accessLevel" : "public",
    "D_attributes" : [

    ],
    "F_location" : "MatcherFunc.swift - Line: 16, Column: 5",
    "G_members" : [

    ],
    "I_parameterType" : [
      "@escaping (Expression<T>, FailureMessage) throws -> Bool"
    ],
    "I_parameters" : [
      "_"
    ]
  },
  {
    "A_name" : "matches",
    "B_kind" : "function",
    "C_accessLevel" : "public",
    "D_attributes" : [

    ],
    "F_location" : "MatcherFunc.swift - Line: 20, Column: 5",
    "G_members" : [

    ],
    "I_parameterType" : [
      "Expression<T>",
      "FailureMessage"
    ],
    "I_parameters" : [
      "_",
      "failureMessage"
    ],
    "J_returnType" : "-> Bool"
  },
  {
    "A_name" : "doesNotMatch",
    "B_kind" : "function",
    "C_accessLevel" : "public",
    "D_attributes" : [

    ],
    "F_location" : "MatcherFunc.swift - Line: 24, Column: 5",
    "G_members" : [

    ],
    "I_parameterType" : [
      "Expression<T>",
      "FailureMessage"
    ],
    "I_parameters" : [
      "_",
      "failureMessage"
    ],
    "J_returnType" : "-> Bool"
  },
  {
    "A_name" : "predicate",
    "B_kind" : "variable",
    "C_accessLevel" : "public",
    "D_attributes" : [
      "available"
    ],
    "F_location" : "MatcherFunc.swift - Line: 31, Column: 5",
    "H_initialValue" : ""
  },
  {
    "A_name" : "NonNilMatcherFunc",
    "B_kind" : "struct",
    "C_accessLevel" : "public",
    "D_attributes" : [
      "available"
    ],
    "E_adoptedClassProtocols" : [
      "Matcher"
    ],
    "F_location" : "MatcherFunc.swift - Line: 48, Column: 1",
    "G_members" : [
      {
        "A_name" : "matcher",
        "B_kind" : "variable",
        "C_accessLevel" : "public",
        "D_attributes" : [

        ],
        "F_location" : "MatcherFunc.swift - Line: 50, Column: 5",
        "H_initialValue" : ""
      },
      {
        "A_name" : "init",
        "B_kind" : "function",
        "C_accessLevel" : "public",
        "D_attributes" : [

        ],
        "F_location" : "MatcherFunc.swift - Line: 52, Column: 5",
        "G_members" : [

        ],
        "I_parameterType" : [
          "@escaping (Expression<T>, FailureMessage) throws -> Bool"
        ],
        "I_parameters" : [
          "_"
        ]
      },
      {
        "A_name" : "matches",
        "B_kind" : "function",
        "C_accessLevel" : "public",
        "D_attributes" : [

        ],
        "F_location" : "MatcherFunc.swift - Line: 56, Column: 5",
        "G_members" : [
          {
            "A_name" : "pass",
            "B_kind" : "variable",
            "C_accessLevel" : "internal",
            "D_attributes" : [

            ],
            "F_location" : "MatcherFunc.swift - Line: 57, Column: 9",
            "H_initialValue" : "try matcher(actualExpression, failureMessage)"
          }
        ],
        "I_parameterType" : [
          "Expression<T>",
          "FailureMessage"
        ],
        "I_parameters" : [
          "_",
          "failureMessage"
        ],
        "J_returnType" : "-> Bool"
      },
      {
        "A_name" : "doesNotMatch",
        "B_kind" : "function",
        "C_accessLevel" : "public",
        "D_attributes" : [

        ],
        "F_location" : "MatcherFunc.swift - Line: 64, Column: 5",
        "G_members" : [
          {
            "A_name" : "pass",
            "B_kind" : "variable",
            "C_accessLevel" : "internal",
            "D_attributes" : [

            ],
            "F_location" : "MatcherFunc.swift - Line: 65, Column: 9",
            "H_initialValue" : "try !matcher(actualExpression, failureMessage)"
          }
        ],
        "I_parameterType" : [
          "Expression<T>",
          "FailureMessage"
        ],
        "I_parameters" : [
          "_",
          "failureMessage"
        ],
        "J_returnType" : "-> Bool"
      },
      {
        "A_name" : "attachNilErrorIfNeeded",
        "B_kind" : "function",
        "C_accessLevel" : "internal",
        "D_attributes" : [

        ],
        "F_location" : "MatcherFunc.swift - Line: 72, Column: 5",
        "G_members" : [

        ],
        "I_parameterType" : [
          "Expression<T>",
          "FailureMessage"
        ],
        "I_parameters" : [
          "_",
          "failureMessage"
        ],
        "J_returnType" : "-> Bool"
      },
      {
        "A_name" : "predicate",
        "B_kind" : "variable",
        "C_accessLevel" : "public",
        "D_attributes" : [
          "available"
        ],
        "F_location" : "MatcherFunc.swift - Line: 83, Column: 5",
        "H_initialValue" : ""
      }
    ]
  },
  {
    "A_name" : "matcher",
    "B_kind" : "variable",
    "C_accessLevel" : "public",
    "D_attributes" : [

    ],
    "F_location" : "MatcherFunc.swift - Line: 50, Column: 5",
    "H_initialValue" : ""
  },
  {
    "A_name" : "init",
    "B_kind" : "function",
    "C_accessLevel" : "public",
    "D_attributes" : [

    ],
    "F_location" : "MatcherFunc.swift - Line: 52, Column: 5",
    "G_members" : [

    ],
    "I_parameterType" : [
      "@escaping (Expression<T>, FailureMessage) throws -> Bool"
    ],
    "I_parameters" : [
      "_"
    ]
  },
  {
    "A_name" : "matches",
    "B_kind" : "function",
    "C_accessLevel" : "public",
    "D_attributes" : [

    ],
    "F_location" : "MatcherFunc.swift - Line: 56, Column: 5",
    "G_members" : [
      {
        "A_name" : "pass",
        "B_kind" : "variable",
        "C_accessLevel" : "internal",
        "D_attributes" : [

        ],
        "F_location" : "MatcherFunc.swift - Line: 57, Column: 9",
        "H_initialValue" : "try matcher(actualExpression, failureMessage)"
      }
    ],
    "I_parameterType" : [
      "Expression<T>",
      "FailureMessage"
    ],
    "I_parameters" : [
      "_",
      "failureMessage"
    ],
    "J_returnType" : "-> Bool"
  },
  {
    "A_name" : "pass",
    "B_kind" : "variable",
    "C_accessLevel" : "internal",
    "D_attributes" : [

    ],
    "F_location" : "MatcherFunc.swift - Line: 57, Column: 9",
    "H_initialValue" : "try matcher(actualExpression, failureMessage)"
  },
  {
    "A_name" : "doesNotMatch",
    "B_kind" : "function",
    "C_accessLevel" : "public",
    "D_attributes" : [

    ],
    "F_location" : "MatcherFunc.swift - Line: 64, Column: 5",
    "G_members" : [
      {
        "A_name" : "pass",
        "B_kind" : "variable",
        "C_accessLevel" : "internal",
        "D_attributes" : [

        ],
        "F_location" : "MatcherFunc.swift - Line: 65, Column: 9",
        "H_initialValue" : "try !matcher(actualExpression, failureMessage)"
      }
    ],
    "I_parameterType" : [
      "Expression<T>",
      "FailureMessage"
    ],
    "I_parameters" : [
      "_",
      "failureMessage"
    ],
    "J_returnType" : "-> Bool"
  },
  {
    "A_name" : "pass",
    "B_kind" : "variable",
    "C_accessLevel" : "internal",
    "D_attributes" : [

    ],
    "F_location" : "MatcherFunc.swift - Line: 65, Column: 9",
    "H_initialValue" : "try !matcher(actualExpression, failureMessage)"
  },
  {
    "A_name" : "attachNilErrorIfNeeded",
    "B_kind" : "function",
    "C_accessLevel" : "internal",
    "D_attributes" : [

    ],
    "F_location" : "MatcherFunc.swift - Line: 72, Column: 5",
    "G_members" : [

    ],
    "I_parameterType" : [
      "Expression<T>",
      "FailureMessage"
    ],
    "I_parameters" : [
      "_",
      "failureMessage"
    ],
    "J_returnType" : "-> Bool"
  },
  {
    "A_name" : "predicate",
    "B_kind" : "variable",
    "C_accessLevel" : "public",
    "D_attributes" : [
      "available"
    ],
    "F_location" : "MatcherFunc.swift - Line: 83, Column: 5",
    "H_initialValue" : ""
  }
]