[
  {
    "A_name" : "NetworkActivityChangeType",
    "B_kind" : "enum",
    "C_accessLevel" : "public",
    "D_attributes" : [

    ],
    "E_adoptedClassProtocols" : [

    ],
    "F_location" : "NetworkActivityPlugin.swift - Line: 4, Column: 1",
    "G_members" : [
      {
        "A_name" : "began",
        "B_kind" : "case",
        "C_accessLevel" : "internal",
        "D_attributes" : [

        ],
        "F_location" : "NetworkActivityPlugin.swift - Line: 5, Column: 10",
        "I_parameterType" : [

        ],
        "I_parameters" : [

        ]
      },
      {
        "A_name" : "ended",
        "B_kind" : "case",
        "C_accessLevel" : "internal",
        "D_attributes" : [

        ],
        "F_location" : "NetworkActivityPlugin.swift - Line: 5, Column: 17",
        "I_parameterType" : [

        ],
        "I_parameters" : [

        ]
      }
    ]
  },
  {
    "A_name" : "NetworkActivityPlugin",
    "B_kind" : "class",
    "C_accessLevel" : "public",
    "D_attributes" : [
      "final"
    ],
    "E_adoptedClassProtocols" : [
      "PluginType"
    ],
    "F_location" : "NetworkActivityPlugin.swift - Line: 9, Column: 1",
    "G_members" : [
      {
        "A_name" : "networkActivityClosure",
        "B_kind" : "variable",
        "C_accessLevel" : "internal",
        "D_attributes" : [

        ],
        "F_location" : "NetworkActivityPlugin.swift - Line: 12, Column: 5",
        "H_initialValue" : ""
      },
      {
        "A_name" : "init",
        "B_kind" : "function",
        "C_accessLevel" : "public",
        "D_attributes" : [

        ],
        "F_location" : "NetworkActivityPlugin.swift - Line: 15, Column: 5",
        "G_members" : [

        ],
        "I_parameterType" : [
          "@escaping NetworkActivityClosure"
        ],
        "I_parameters" : [
          "networkActivityClosure"
        ]
      },
      {
        "A_name" : "willSend",
        "B_kind" : "function",
        "C_accessLevel" : "public",
        "D_attributes" : [

        ],
        "F_location" : "NetworkActivityPlugin.swift - Line: 22, Column: 5",
        "G_members" : [

        ],
        "I_parameterType" : [
          "RequestType",
          "TargetType"
        ],
        "I_parameters" : [
          "_",
          "target"
        ]
      },
      {
        "A_name" : "didReceive",
        "B_kind" : "function",
        "C_accessLevel" : "public",
        "D_attributes" : [

        ],
        "F_location" : "NetworkActivityPlugin.swift - Line: 27, Column: 5",
        "G_members" : [

        ],
        "I_parameterType" : [
          "Result<Moya.Response, MoyaError>",
          "TargetType"
        ],
        "I_parameters" : [
          "_",
          "target"
        ]
      }
    ]
  },
  {
    "A_name" : "networkActivityClosure",
    "B_kind" : "variable",
    "C_accessLevel" : "internal",
    "D_attributes" : [

    ],
    "F_location" : "NetworkActivityPlugin.swift - Line: 12, Column: 5",
    "H_initialValue" : ""
  },
  {
    "A_name" : "init",
    "B_kind" : "function",
    "C_accessLevel" : "public",
    "D_attributes" : [

    ],
    "F_location" : "NetworkActivityPlugin.swift - Line: 15, Column: 5",
    "G_members" : [

    ],
    "I_parameterType" : [
      "@escaping NetworkActivityClosure"
    ],
    "I_parameters" : [
      "networkActivityClosure"
    ]
  },
  {
    "A_name" : "willSend",
    "B_kind" : "function",
    "C_accessLevel" : "public",
    "D_attributes" : [

    ],
    "F_location" : "NetworkActivityPlugin.swift - Line: 22, Column: 5",
    "G_members" : [

    ],
    "I_parameterType" : [
      "RequestType",
      "TargetType"
    ],
    "I_parameters" : [
      "_",
      "target"
    ]
  },
  {
    "A_name" : "didReceive",
    "B_kind" : "function",
    "C_accessLevel" : "public",
    "D_attributes" : [

    ],
    "F_location" : "NetworkActivityPlugin.swift - Line: 27, Column: 5",
    "G_members" : [

    ],
    "I_parameterType" : [
      "Result<Moya.Response, MoyaError>",
      "TargetType"
    ],
    "I_parameters" : [
      "_",
      "target"
    ]
  }
]